depswiz/__init__.py
depswiz/__main__.py
depswiz/py.typed
depswiz/ai/__init__.py
depswiz/ai/claude_client.py
depswiz/ai/prompts.py
depswiz/cli/__init__.py
depswiz/cli/app.py
depswiz/cli/context.py
depswiz/cli/commands/__init__.py
depswiz/cli/commands/audit.py
depswiz/cli/commands/check.py
depswiz/cli/commands/deprecations.py
depswiz/cli/commands/guide.py
depswiz/cli/commands/licenses.py
depswiz/cli/commands/plugins.py
depswiz/cli/commands/sbom.py
depswiz/cli/commands/suggest.py
depswiz/cli/commands/tools.py
depswiz/cli/commands/update.py
depswiz/cli/formatters/__init__.py
depswiz/cli/formatters/base.py
depswiz/cli/formatters/cli.py
depswiz/cli/formatters/html.py
depswiz/cli/formatters/json.py
depswiz/cli/formatters/markdown.py
depswiz/cli/formatters/sarif.py
depswiz/core/__init__.py
depswiz/core/cache.py
depswiz/core/config.py
depswiz/core/logging.py
depswiz/core/models.py
depswiz/core/scanner.py
depswiz/core/version.py
depswiz/deprecations/__init__.py
depswiz/deprecations/models.py
depswiz/deprecations/scanner.py
depswiz/guide/__init__.py
depswiz/guide/app.py
depswiz/guide/chat.py
depswiz/guide/context.py
depswiz/guide/engine.py
depswiz/guide/fallback.py
depswiz/guide/state.py
depswiz/guide/screens/__init__.py
depswiz/guide/screens/ai_screen.py
depswiz/guide/screens/audit_screen.py
depswiz/guide/screens/chat_screen.py
depswiz/guide/screens/licenses_screen.py
depswiz/guide/screens/tools_screen.py
depswiz/guide/screens/updates_screen.py
depswiz/guide/screens/welcome_screen.py
depswiz/guide/styles/base.tcss
depswiz/guide/widgets/__init__.py
depswiz/guide/widgets/health_score.py
depswiz/guide/widgets/license_panel.py
depswiz/guide/widgets/tools_panel.py
depswiz/guide/widgets/updates_panel.py
depswiz/guide/widgets/vulnerability_panel.py
depswiz/monorepo/__init__.py
depswiz/monorepo/detector.py
depswiz/plugins/__init__.py
depswiz/plugins/base.py
depswiz/plugins/registry.py
depswiz/plugins/dart/__init__.py
depswiz/plugins/dart/plugin.py
depswiz/plugins/docker/__init__.py
depswiz-0.5.0.dist-info/METADATA
depswiz-0.5.0.dist-info/WHEEL
depswiz-0.5.0.dist-info/entry_points.txt
depswiz-0.5.0.dist-info/licenses/LICENSE
depswiz-0.5.0.dist-info/RECORD
