Metadata-Version: 2.4
Name: depswiz
Version: 0.5.0
Summary: Multi-language dependency wizard - check, audit, and update dependencies across Python, Rust, Dart, and JavaScript ecosystems
Project-URL: Homepage, https://github.com/moinsen-dev/depswiz
Project-URL: Documentation, https://moinsen-dev.github.io/depswiz
Project-URL: Repository, https://github.com/moinsen-dev/depswiz
Project-URL: Issues, https://github.com/moinsen-dev/depswiz/issues
Author: depswiz contributors
License-Expression: MIT
License-File: LICENSE
Keywords: audit,dart,dependencies,javascript,monorepo,python,rust,sbom,security,typescript,vulnerability
Classifier: Development Status :: 4 - Beta
Classifier: Environment :: Console
Classifier: Intended Audience :: Developers
Classifier: License :: OSI Approved :: MIT License
Classifier: Operating System :: OS Independent
Classifier: Programming Language :: Python :: 3
Classifier: Programming Language :: Python :: 3.13
Classifier: Topic :: Security
Classifier: Topic :: Software Development :: Build Tools
Classifier: Topic :: Software Development :: Quality Assurance
Classifier: Typing :: Typed
Requires-Python: >=3.13
Requires-Dist: anyio>=4.0.0
Requires-Dist: cyclonedx-python-lib>=11.0.0
Requires-Dist: diskcache>=5.6.0
Requires-Dist: httpx>=0.27.0
Requires-Dist: inquirerpy>=0.3.4
Requires-Dist: packaging>=24.0
Requires-Dist: pyyaml>=6.0.0
Requires-Dist: rich>=13.9.0
Requires-Dist: semver>=3.0.0
Requires-Dist: textual>=0.89.0
Requires-Dist: typer>=0.15.0
Provides-Extra: dev
Requires-Dist: mypy>=1.13.0; extra == 'dev'
Requires-Dist: pre-commit>=4.0.0; extra == 'dev'
Requires-Dist: pytest-asyncio>=0.24.0; extra == 'dev'
Requires-Dist: pytest-cov>=5.0.0; extra == 'dev'
Requires-Dist: pytest>=8.0.0; extra == 'dev'
Requires-Dist: ruff>=0.8.0; extra == 'dev'
Provides-Extra: docs
Requires-Dist: mkdocs-material>=9.5.0; extra == 'docs'
Requires-Dist: mkdocs>=1.6.0; extra == 'docs'
